setup.py
Sonance_Music_Player.egg-info/PKG-INFO
Sonance_Music_Player.egg-info/SOURCES.txt
Sonance_Music_Player.egg-info/dependency_links.txt
Sonance_Music_Player.egg-info/requires.txt
Sonance_Music_Player.egg-info/top_level.txt
audio/PlaylistManager.py
audio/__init__.py
audio/music_player.py
audio/playlist_models.py
audio_formats/__init__.py
audio_formats/base.py
audio_formats/flac.py
audio_formats/mp3.py
audio_formats/mp4.py
gui/__init__.py
gui/cover_art_display.py
gui/delegates.py
gui/dialogs.py
gui/helper_struct.py
gui/left_sidebar.py
gui/main_window.py
gui/models.py
gui/widgets.py