Metadata-Version: 1.1
Name: Sonance-Music-Player
Version: 0.1.Alpha
Summary: This is a music player using PyQt5
Home-page: https://github.com/gdankov/sonance-music-player
Author: Georgi Dankov
Author-email: gddankov@gmail.com
License: GNU GPL v2
Platform: UNKNOWN
Classifier: Development Status :: 2 - Pre-Alpha
Classifier: Environment :: Console
Classifier: Environment :: X11 Applications :: Qt
Classifier: Intended Audience :: End Users/Desktop
Classifier: Intended Audience :: Developers
Classifier: License :: OSI Approved :: GNU General Public License v2 (GPLv2)
Classifier: Operating System :: MacOS :: MacOS X
Classifier: Operating System :: Microsoft :: Windows
Classifier: Operating System :: POSIX
Classifier: Programming Language :: Python
